runevery/__init__.py
runevery/parser.py
runevery/planners.py
runevery/py.typed
runevery/scheduler.py
runevery/task.py
runevery/utils.py
runevery-0.5.6.dist-info/LICENSE
runevery-0.5.6.dist-info/METADATA
runevery-0.5.6.dist-info/WHEEL
runevery-0.5.6.dist-info/RECORD
