Metadata-Version: 2.3
Name: runevery
Version: 0.5.6
Summary: 
License: MIT
Author: Dmitry Gritsenko
Author-email: runevery@evtn.me
Requires-Python: >=3.8,<4.0
Classifier: License :: OSI Approved :: MIT License
Classifier: Programming Language :: Python :: 3
Classifier: Programming Language :: Python :: 3.8
Classifier: Programming Language :: Python :: 3.9
Classifier: Programming Language :: Python :: 3.10
Classifier: Programming Language :: Python :: 3.11
Classifier: Programming Language :: Python :: 3.12
Classifier: Programming Language :: Python :: 3.13
Requires-Dist: typing-extensions (>=4.12.1,<5.0.0)
Project-URL: Homepage, https://github.com/evtn/runevery
Project-URL: Repository, https://github.com/evtn/runevery
